{
  "created_at": "2024-08-09T08:39:17.040278+00:00",
  "creator": {
    "displayname": "aravinth_ravikumar",
    "id": 5,
    "orcid": null
  },
  "description": "Implements the model specified by the article I_The prediction of atmospheric corrosion from meteorological and pollution parameters—I. Annual corrosion",
  "extras": [
    {
      "key": "model_parameters",
      "type": "dict",
      "value": [
        {
          "key": "Time",
          "type": "dict",
          "value": [
            {
              "key": "default value",
              "type": "str",
              "value": "10"
            },
            {
              "key": "symbol",
              "type": "str",
              "value": "time"
            },
            {
              "key": "unit",
              "type": "str",
              "value": "years"
            }
          ]
        },
        {
          "key": "Binary Interaction",
          "type": "bool",
          "value": null
        },
        {
          "key": "Wetness time",
          "type": "dict",
          "value": [
            {
              "key": "default value",
              "type": "str",
              "value": "0.4"
            },
            {
              "key": "symbol",
              "type": "str",
              "value": "T_w"
            },
            {
              "key": "unit",
              "type": "str",
              "value": "annual fraction"
            }
          ]
        },
        {
          "key": "Temperature",
          "type": "dict",
          "value": [
            {
              "key": "default value",
              "type": "str",
              "value": "20"
            },
            {
              "key": "symbol",
              "type": "str",
              "value": "T"
            },
            {
              "key": "unit",
              "type": "str",
              "value": "°C"
            }
          ]
        },
        {
          "key": "Atmosphere",
          "type": "list",
          "value": [
            {
              "type": "list",
              "value": [
                {
                  "type": "str",
                  "value": "Rural Atmosphere ( $Cl < 0.1 mg Cl^{-} dm^{-2} d^{-1}$ and $S0_2 < mg SO_2^ dm^{-2} d^{-1}$)"
                },
                {
                  "type": "dict",
                  "value": [
                    {
                      "key": "default value",
                      "type": "str",
                      "value": "table_2[7,3]"
                    },
                    {
                      "key": "unit",
                      "type": "str",
                      "value": "[mg Cl^{-} dm^{-2} d^{-1}]"
                    },
                    {
                      "key": "symbol",
                      "type": "str",
                      "value": "Cl^-"
                    },
                    {
                      "key": "parameter",
                      "type": "str",
                      "value": "Chloride pollution annual average"
                    }
                  ]
                },
                {
                  "type": "dict",
                  "value": [
                    {
                      "key": "default value",
                      "type": "str",
                      "value": "table_2[8,3]"
                    },
                    {
                      "key": "unit",
                      "type": "str",
                      "value": "[mg Cl^{-} dm^{-2} d^{-1}]"
                    },
                    {
                      "key": "symbol",
                      "type": "str",
                      "value": "SO_2"
                    },
                    {
                      "key": "parameter",
                      "type": "str",
                      "value": "Sulfur Dioxide pollution annual average"
                    }
                  ]
                }
              ]
            },
            {
              "type": "list",
              "value": [
                {
                  "type": "str",
                  "value": "Urban industrial Atmosphere ( $Cl > 0.1 mg Cl^{-} dm^{-2} d^{-1}$ and $S0_2 < mg SO_2^ dm^{-2} d^{-1}$)"
                },
                {
                  "type": "dict",
                  "value": [
                    {
                      "key": "default value",
                      "type": "str",
                      "value": "table_2[7, 3]"
                    },
                    {
                      "key": "unit",
                      "type": "str",
                      "value": "[mg Cl^{-} dm^{-2} d^{-1}]"
                    },
                    {
                      "key": "symbol",
                      "type": "str",
                      "value": "Cl^-"
                    },
                    {
                      "key": "parameter",
                      "type": "str",
                      "value": "Chloride pollution annual average"
                    }
                  ]
                },
                {
                  "type": "dict",
                  "value": [
                    {
                      "key": "default value",
                      "type": "str",
                      "value": "table_2[8, 3]"
                    },
                    {
                      "key": "unit",
                      "type": "str",
                      "value": "[mg Cl^{-} dm^{-2} d^{-1}]"
                    },
                    {
                      "key": "symbol",
                      "type": "str",
                      "value": "SO_2"
                    },
                    {
                      "key": "parameter",
                      "type": "str",
                      "value": "Sulfur Dioxide pollution annual average"
                    }
                  ]
                }
              ]
            },
            {
              "type": "list",
              "value": [
                {
                  "type": "str",
                  "value": "Marine Atmosphere ( $Cl > 0.1 mg Cl^{-} dm^{-2} d^{-1}$ )"
                },
                {
                  "type": "dict",
                  "value": [
                    {
                      "key": "default value",
                      "type": "str",
                      "value": "table_2[7, 3]"
                    },
                    {
                      "key": "unit",
                      "type": "str",
                      "value": "[mg Cl^{-} dm^{-2} d^{-1}]"
                    },
                    {
                      "key": "symbol",
                      "type": "str",
                      "value": "Cl^-"
                    },
                    {
                      "key": "parameter",
                      "type": "str",
                      "value": "Chloride pollution annual average"
                    }
                  ]
                },
                {
                  "type": "dict",
                  "value": [
                    {
                      "key": "default value",
                      "type": "str",
                      "value": "table_2[8, 3]"
                    },
                    {
                      "key": "unit",
                      "type": "str",
                      "value": "[mg Cl^{-} dm^{-2} d^{-1}]"
                    },
                    {
                      "key": "symbol",
                      "type": "str",
                      "value": "SO_2"
                    },
                    {
                      "key": "parameter",
                      "type": "str",
                      "value": "Sulfur Dioxide pollution annual average"
                    }
                  ]
                }
              ]
            },
            {
              "type": "list",
              "value": [
                {
                  "type": "str",
                  "value": "[User Entry] Enter Cl^- and SO_2 pollution annual averages"
                },
                {
                  "type": "dict",
                  "value": [
                    {
                      "key": "linked to",
                      "type": "str",
                      "value": "Atmosphere"
                    },
                    {
                      "key": "linked value",
                      "type": "str",
                      "value": "4"
                    },
                    {
                      "key": "default value",
                      "type": "str",
                      "value": "table_2[7, 3]"
                    },
                    {
                      "key": "unit",
                      "type": "str",
                      "value": "[mg Cl^{-} dm^{-2} d^{-1}]"
                    },
                    {
                      "key": "symbol",
                      "type": "str",
                      "value": "Cl^-"
                    },
                    {
                      "key": "parameter",
                      "type": "str",
                      "value": "Chloride pollution annual average"
                    }
                  ]
                },
                {
                  "type": "dict",
                  "value": [
                    {
                      "key": "linked to",
                      "type": "str",
                      "value": "Atmosphere"
                    },
                    {
                      "key": "linked value",
                      "type": "str",
                      "value": "4"
                    },
                    {
                      "key": "default value",
                      "type": "str",
                      "value": "table_2[8, 3]"
                    },
                    {
                      "key": "unit",
                      "type": "str",
                      "value": "[mg Cl^{-} dm^{-2} d^{-1}]"
                    },
                    {
                      "key": "symbol",
                      "type": "str",
                      "value": "SO_2"
                    },
                    {
                      "key": "parameter",
                      "type": "str",
                      "value": "Sulfur Dioxide pollution annual average"
                    }
                  ]
                }
              ]
            }
          ]
        },
        {
          "key": "[display] Binary Interaction formula 1",
          "type": "dict",
          "value": [
            {
              "key": "linked to",
              "type": "str",
              "value": "Binary Interaction"
            },
            {
              "key": "linked value",
              "type": "str",
              "value": "True"
            },
            {
              "key": "formula",
              "type": "str",
              "value": "Annual corrosion, A $[um]$ = $132.4Cl^-(1 + 0.038T - 1.96t_w - 0.53SO_2 + 74.6t_w(1 + 1.07SO_2) - 6.3)$"
            }
          ]
        },
        {
          "key": "[display] Binary Interaction formula 2",
          "type": "dict",
          "value": [
            {
              "key": "linked to",
              "type": "str",
              "value": "Binary Interaction"
            },
            {
              "key": "linked value",
              "type": "str",
              "value": "False"
            },
            {
              "key": "formula",
              "type": "str",
              "value": "Annual corrosion, A $[um]$ = $33.0 + 57.4Cl^- + 26.6SO_2$"
            }
          ]
        },
        {
          "key": "[display] Exponent formula 1",
          "type": "dict",
          "value": [
            {
              "key": "formula",
              "type": "str",
              "value": "Exponent, n = $0.570 + 0.0057Cl^-T + 7.7 \\times 10^{-4}T_w*365 - 1.7 \\times 10^{-3}A$"
            }
          ]
        }
      ]
    }
  ],
  "files": [],
  "id": 218,
  "identifier": "model-i_the_prediction_of_atmospheric_corrosion_fr",
  "last_modified": "2024-08-13T07:12:36.096125+00:00",
  "license": null,
  "links": [],
  "tags": [
    "corrosion",
    "corwiz",
    "models"
  ],
  "title": "model I_The prediction of atmospheric corrosion from meteorological and pollution parameters—I. Annual corrosion",
  "type": "corwiz_model"
}